sphinxcontrib_apa-1.0.0-nspkg.pth
sphinxcontrib/apa.py
sphinxcontrib_apa-1.0.0.dist-info/LICENSE
sphinxcontrib_apa-1.0.0.dist-info/METADATA
sphinxcontrib_apa-1.0.0.dist-info/WHEEL
sphinxcontrib_apa-1.0.0.dist-info/namespace_packages.txt
sphinxcontrib_apa-1.0.0.dist-info/top_level.txt
sphinxcontrib_apa-1.0.0.dist-info/RECORD
