Metadata-Version: 2.1
Name: sphinxcontrib-apa
Version: 1.0.0
Summary: Simple APA citation style for Sphinx and Jupyter Book
Home-page: UNKNOWN
Author: Jean M. Lescure
License: Apache-2.0
Platform: UNKNOWN
Classifier: License :: OSI Approved :: Apache Software License
Classifier: Operating System :: OS Independent
Classifier: Programming Language :: Python :: 3
Classifier: Topic :: Documentation
Classifier: Topic :: Utilities
Requires-Python: >=3.6
